licaplot/__init__.py
licaplot/_version.py
licaplot/csv.py
licaplot/filters.py
licaplot/hamamatsu.py
licaplot/osi.py
licaplot/photod.py
licaplot/tessw.py
licaplot/resources/__init__.py
licaplot/resources/global.mplstyle
licaplot/utils/__init__.py
licaplot/utils/mpl.py
licaplot/utils/parser.py
licaplot/utils/processing.py
licaplot/utils/validators.py
licaplot-0.2.12.dist-info/LICENSE
licaplot-0.2.12.dist-info/METADATA
licaplot-0.2.12.dist-info/WHEEL
licaplot-0.2.12.dist-info/entry_points.txt
licaplot-0.2.12.dist-info/top_level.txt
licaplot-0.2.12.dist-info/RECORD
