Metadata-Version: 2.2
Name: licaplot
Version: 0.2.12
Summary: Plotting tools to analyze sensors and filters from LICA Optical Bench
Author-email: Rafael González <rafael08@ucm.es>, Jaime Zamorano <jzamoran@ucm.es>
License: GPL-3.0 license
Project-URL: Homepage, https://github.com/guaix-ucm/licaplot
Project-URL: Repository, https://github.com/guaix-ucm/licaplot.git
Classifier: Programming Language :: Python :: 3.9
Classifier: Programming Language :: Python :: 3.10
Classifier: Programming Language :: Python :: 3.11
Classifier: Programming Language :: Python :: 3.12
Classifier: Development Status :: 4 - Beta
Classifier: Environment :: Console
Classifier: Intended Audience :: Science/Research
Classifier: License :: OSI Approved :: GNU General Public License (GPL)
Classifier: Operating System :: OS Independent
Classifier: Topic :: Scientific/Engineering :: Astronomy
Classifier: Topic :: Scientific/Engineering :: Atmospheric Science
Requires-Python: >=3.9
License-File: LICENSE
Requires-Dist: matplotlib
Requires-Dist: PyQt5
Requires-Dist: astropy
Requires-Dist: scipy
Requires-Dist: lica[lica]
